{
  "7ed6666c1ddb30f0": {
    "username": "guest",
    "filename": "/Users/raejae/Desktop/shareFile/uploads/guests/6ca98e177637/2023-07-06.jpg.enc",
    "hash": "$2a$10$kqK0iVLarV7VuWLqnzzTbu1VO7YHBomd/HxeVeyDmYptW2EBGwTJm",
    "expires": 1759349094745
  },
  "users": {
    "admin": [
      {
        "file": "1759354686189-2023-07-06.jpg.enc",
        "original": "2023-07-06.jpg",
        "uploaded": 1759354686194
      },
      {
        "file": "1759356618594-2023-07-06.jpg.enc",
        "original": "2023-07-06.jpg",
        "label": "test",
        "uploaded": 1759356618599
      },
      {
        "file": "1759385805179-521205544_23993943253600539_7463007272032373473_n.jpg.enc",
        "original": "521205544_23993943253600539_7463007272032373473_n.jpg",
        "label": "U Naing",
        "uploaded": 1759385805182
      }
    ],
    "raejae": [
      {
        "file": "1759274534017-2023-07-06.jpg.enc",
        "original": "2023-07-06.jpg",
        "label": "Sushi",
        "uploaded": 1759274534026
      },
      {
        "file": "1759275139008-522204823_23993940240267507_8136506297108458932_n.jpg.enc",
        "original": "522204823_23993940240267507_8136506297108458932_n.jpg",
        "label": "photo",
        "uploaded": 1759275139014
      },
      {
        "file": "1759356503146-admin (7).zip.enc",
        "original": "admin (7).zip",
        "label": "Project file",
        "uploaded": 1759356503395
      },
      {
        "file": "1759386599872-522204823_23993940240267507_8136506297108458932_n.jpg.enc",
        "original": "522204823_23993940240267507_8136506297108458932_n.jpg",
        "label": "home wed",
        "uploaded": 1759386599876
      },
      {
        "file": "1759396603509-521205544_23993943253600539_7463007272032373473_n.jpg.enc",
        "original": "521205544_23993943253600539_7463007272032373473_n.jpg",
        "label": "photo",
        "uploaded": 1759396603513
      },
      {
        "file": "1759397290278-2025-05-31.jpg.enc",
        "original": "2025-05-31.jpg",
        "label": "sushi",
        "uploaded": 1759397290387,
        "hash": "$2a$10$9kQdVYmlZyVILeWkhz/XbuNTdObp1vWrRmiK4ugb1kAYx.rN6mDs2"
      },
      {
        "file": "1759397406069-2023-07-06.jpg.enc",
        "original": "2023-07-06.jpg",
        "label": "New testing sushi",
        "uploaded": 1759397406174,
        "hash": "$2a$10$f0L57c4Dn8S5nb8nNuKOb.oN2j5JsjruPhjl1X4xGnkRUVdV96zPe"
      },
      {
        "file": "1759397465230-522204823_23993940240267507_8136506297108458932_n.jpg.enc",
        "original": "522204823_23993940240267507_8136506297108458932_n.jpg",
        "label": "No password",
        "uploaded": 1759397465233,
        "hash": null
      },
      {
        "file": "1759397938445-2025-05-31.jpg.enc",
        "original": "2025-05-31.jpg",
        "label": "Password ",
        "uploaded": 1759397938557,
        "hash": "$2a$10$588Xgh9KJFkEnCl3ryf23uOG759YS.F6iwOv841ByYzNhLj.baB76"
      }
    ],
    "htet": [
      {
        "file": "1759385609946-522204823_23993940240267507_8136506297108458932_n.jpg.enc",
        "original": "522204823_23993940240267507_8136506297108458932_n.jpg",
        "label": "This is our wedding photo",
        "uploaded": 1759385609951
      },
      {
        "file": "1759386073937-2025-05-31.jpg.enc",
        "original": "2025-05-31.jpg",
        "label": "sashimi",
        "uploaded": 1759386073945
      }
    ],
    "lin": []
  },
  "guests": {}
}